oogway_py-0.1.1.dist-info/METADATA
oogway_py-0.1.1.dist-info/WHEEL
oogway_py/demo.py
oogway_py/__init__.py
oogway_py/oogway_py.cpython-38-arm-linux-gnueabihf.so
oogway_py-0.1.1.dist-info/RECORD
